tests/__init__.py
tests/models/__init__.py
tests/models/test_redirect_relu.py
torchbearer_visual-0.1.0.dist-info/METADATA
torchbearer_visual-0.1.0.dist-info/RECORD
torchbearer_visual-0.1.0.dist-info/WHEEL
torchbearer_visual-0.1.0.dist-info/top_level.txt
visual/__init__.py
visual/ascent.py
visual/images.py
visual/loss.py
visual/redirect_relu.py
visual/transforms.py
visual/version.py
visual/models/__init__.py
visual/models/alexnet.py
visual/models/densenet.py
visual/models/googlenet.py
visual/models/inception.py
visual/models/mobilenet.py
visual/models/resnet.py
visual/models/shufflenetv2.py
visual/models/squeezenet.py
visual/models/utils.py
visual/models/vgg.py
