Metadata-Version: 2.1
Name: torchbearer-visual
Version: 0.1.0
Summary: A visualisation library for PyTorch using torchbearer
Home-page: https://github.com/pytorchbearer/visual
Author: Ethan Harris
Author-email: ewah1g13@ecs.soton.ac.uk
License: MIT
Download-URL: https://github.com/pytorchbearer/visual/archive/0.1.0.tar.gz
Platform: UNKNOWN
Requires-Python: >=2.7,!=3.0.*,!=3.1.*,!=3.2.*,!=3.3.*,!=3.4.*
Requires-Dist: torch (>=1.1.0)
Requires-Dist: torchvision (>=0.3.0)
Requires-Dist: torchbearer
